{
    "field_weights": {
        "authors": 0.7096813835286331,
        "concat_authors_title_venue_year": 0.12548719295170294,
        "title": 0.1600496279712105,
        "venue": 0.004781795548453575
    },
    "best_query_spec": {
        "field_analyzer_mapping": {
            "authors": [
                "authors.3gram"
            ],
            "title": [
                "concat_authors_title_venue_year.standard"
            ]
        },
        "boost_map": {},
        "filter_config": []
    },
    "performance_score": 0.2939783486321166,
    "optimization_metadata": {
        "confidence_level": 0.99,
        "sample_size": 10000,
        "max_combination_size": 3,
        "optimization_query_limit": 250
    },
    "index_config_summary": {
        "field_to_analyzers": {
            "title": [
                "standard",
                "3gram"
            ],
            "authors": [
                "standard",
                "3gram"
            ],
            "venue": [
                "standard",
                "3gram"
            ],
            "year": [
                "standard",
                "3gram"
            ],
            "concat_authors_title_venue_year": [
                "standard",
                "3gram"
            ]
        },
        "concat_fields": {
            "concat_authors_title_venue_year": [
                "title",
                "authors",
                "venue",
                "year"
            ]
        },
        "default_analyzer": "standard",
        "similarity_config": {
            "type": "BM25",
            "b": 0.75,
            "k1": 1.2
        },
        "id_column": "_id"
    }
}